monotable/__init__.py
monotable/alignment.py
monotable/cellerror.py
monotable/datacls.py
monotable/mono.py
monotable/monoblock.py
monotable/plugin.py
monotable/py.typed
monotable/scanner.py
monotable/table.py
monotable-3.2.0.dist-info/LICENSE
monotable-3.2.0.dist-info/METADATA
monotable-3.2.0.dist-info/WHEEL
monotable-3.2.0.dist-info/top_level.txt
monotable-3.2.0.dist-info/RECORD
