Metadata-Version: 2.1
Name: monotable
Version: 3.2.0
Summary: ASCII table with per column format specs and more.
Home-page: https://monotable.readthedocs.io/en/latest/
Author: Mark Taylor
Author-email: mark66547ta2@gmail.com
License: MIT
Project-URL: Bug Reports, https://github.com/tmarktaylor/monotable/issues
Project-URL: Source, https://github.com/tmarktaylor/monotable/
Keywords: ascii,table,pretty
Classifier: Development Status :: 5 - Production/Stable
Classifier: License :: OSI Approved :: Apache Software License
Classifier: Operating System :: OS Independent
Classifier: Intended Audience :: Developers
Classifier: Topic :: Software Development :: Libraries
Classifier: Topic :: Software Development :: Libraries :: Python Modules
Classifier: Topic :: Utilities
Classifier: Programming Language :: Python :: 3 :: Only
Classifier: Programming Language :: Python :: 3.7
Classifier: Programming Language :: Python :: 3.8
Classifier: Programming Language :: Python :: 3.9
Classifier: Programming Language :: Python :: 3.10
Classifier: Programming Language :: Python :: 3.11
Classifier: Programming Language :: Python :: 3.12
Classifier: Programming Language :: Python :: Implementation :: PyPy
Requires-Python: >=3.7
License-File: LICENSE
